{
  "project_info": {
    "project_number": "199536267599",
    "firebase_url": "https://cookit-16ecb-default-rtdb.firebaseio.com",
    "project_id": "cookit-16ecb",
    "storage_bucket": "cookit-16ecb.appspot.com"
  },
  "client": [
    {
      "client_info": {
        "mobilesdk_app_id": "1:199536267599:android:97fe8842607ee2535af53a",
        "android_client_info": {
          "package_name": "com.example.cookit"
        }
      },
      "oauth_client": [
        {
          "client_id": "199536267599-ns3cca5v5k29b61eakndhc6tdr0a1sep.apps.googleusercontent.com",
          "client_type": 1,
          "android_info": {
            "package_name": "com.example.cookit",
            "certificate_hash": "fdf1c6f4221d954c04f3d3cac2d17bee739cdd50"
          }
        },
        {
          "client_id": "199536267599-ip4379ku3admraq02eu85dtooq9cv546.apps.googleusercontent.com",
          "client_type": 3
        }
      ],
      "api_key": [
        {
          "current_key": "AIzaSyCXFFWGbN5z7i-wzurGndAh07blJMer32Y"
        }
      ],
      "services": {
        "appinvite_service": {
          "other_platform_oauth_client": [
            {
              "client_id": "199536267599-0tekdpiid4oig2r7m7k3bmqpk7s1jq4f.apps.googleusercontent.com",
              "client_type": 3
            }
          ]
        }
      }
    }
  ],
  "configuration_version": "1"
}